agredadb/__init__.py
agredadb/agreda_pb2.py
agredadb/agreda_pb2_grpc.py
agredadb/client.py
agredadb/ml.py
agredadb-2.0.0.dist-info/licenses/LICENSE
agredadb-2.0.0.dist-info/METADATA
agredadb-2.0.0.dist-info/WHEEL
agredadb-2.0.0.dist-info/top_level.txt
agredadb-2.0.0.dist-info/RECORD
